VeVaPy/DEsolver.py
VeVaPy/__init__.py
VeVaPy/dataImport.py
VeVaPy/optimize.py
VeVaPy/visualize.py
VeVaPy/data_files/.DS_Store
VeVaPy/data_files/Bangsgaard-Ottesen-2017-patient-f-ACTH-data.txt
VeVaPy/data_files/Bangsgaard-Ottesen-2017-patient-f-cortisol-data.txt
VeVaPy/data_files/Bremner-2007-abused-PTSD-cortisol.txt
VeVaPy/data_files/Bremner-2007-non-abused-PTSD-cortisol.txt
VeVaPy/data_files/Bremner-2007-non-abused-non-PTSD-cortisol.txt
VeVaPy/data_files/Carroll-2007-HCDepressedACTH.txt
VeVaPy/data_files/Carroll-2007-HCDepressedCortisol.txt
VeVaPy/data_files/Carroll-2007-LCDepressedACTH.txt
VeVaPy/data_files/Carroll-2007-LCDepressedCortisol.txt
VeVaPy/data_files/Carroll-2007-controlGroupACTH.txt
VeVaPy/data_files/Carroll-2007-controlGroupCortisol.txt
VeVaPy/data_files/Golier-2007-PTSD-ACTH.txt
VeVaPy/data_files/Golier-2007-PTSD-cortisol.txt
VeVaPy/data_files/Golier-2007-non-PTSD-trauma-exposed-ACTH.txt
VeVaPy/data_files/Golier-2007-non-PTSD-trauma-exposed-cortisol.txt
VeVaPy/data_files/Golier-2007-non-exposed-control-ACTH.txt
VeVaPy/data_files/Golier-2007-non-exposed-control-cortisol.txt
VeVaPy/data_files/Yehuda-1996-PTSD-cortisol.txt
VeVaPy/data_files/Yehuda-1996-control-cortisol.txt
VeVaPy/data_files/Yehuda-1996-depressed-cortisol.txt
VeVaPy/data_files/nelson-MDD-subtypes.txt
VeVaPy/data_files/tsst_acth_nelson.txt
VeVaPy/data_files/tsst_cort_nelson.txt
VeVaPy-0.1.3.dist-info/LICENSE
VeVaPy-0.1.3.dist-info/METADATA
VeVaPy-0.1.3.dist-info/WHEEL
VeVaPy-0.1.3.dist-info/top_level.txt
VeVaPy-0.1.3.dist-info/RECORD
