Metadata-Version: 2.1
Name: VeVaPy
Version: 0.1.3
Summary: A Python package for streamlined V&V of HPA axis models.
Author-email: "Christopher Parker (University of Cincinnati)" <parkecp@mail.uc.edu>
License: MIT License
Project-URL: Homepage, https://github.com/cparker-uc/VeVaPy
Classifier: Programming Language :: Python :: 3
Classifier: License :: OSI Approved :: MIT License
Classifier: Operating System :: OS Independent
Classifier: Development Status :: 4 - Beta
Classifier: Intended Audience :: Science/Research
Classifier: Topic :: Scientific/Engineering :: Visualization
Requires-Python: >=3.7
License-File: LICENSE
Requires-Dist: numpy
Requires-Dist: scipy
Requires-Dist: matplotlib
Requires-Dist: IPython
Requires-Dist: Jupyterlab
Requires-Dist: tabulate
Requires-Dist: pandas
